src/emergency_traffic.v
with open('emergency_traffic.v', 'w') as f:
    f.write("""
module emergency_traffic (
    input clk,
    input reset,
    input ped_button,
    input emergency_input, // NEW: Highest Priority
    output reg [2:0] light 
);
    parameter S_GREEN = 2'b00, S_YELLOW = 2'b01, S_RED = 2'b10, S_EMERGENCY = 2'b11;
    reg [1:0] state, next_state;
    reg [3:0] timer; 

    always @(posedge clk or posedge reset) begin
        if (reset) begin
            state <= S_GREEN;
            timer <= 0;
        end else if (emergency_input) begin
            state <= S_GREEN; // Emergency always forces Green to clear traffic
            timer <= 0;
        end else begin
            if (timer == 4'd10 || (state == S_GREEN && ped_button)) begin
                state <= next_state;
                timer <= 0;
            end else begin
                timer <= timer + 1;
            end
        end
    end

    always @(*) begin
        case (state)
            S_GREEN:  next_state = S_YELLOW;
            S_YELLOW: next_state = S_RED;
            S_RED:    next_state = S_GREEN;
            default:  next_state = S_GREEN;
        endcase
    end

    always @(*) begin
        case (state)
            S_GREEN:  light = 3'b001; 
            S_YELLOW: light = 3'b010; 
            S_RED:    light = 3'b100; 
            default:  light = 3'b001;
        endcase
    end
endmodule
""")

tb/tb_emergency.v
with open('tb_emergency.v', 'w') as f:
    f.write("""
module tb_emergency;
    reg clk, reset, ped_button, emergency_input;
    wire [2:0] light;

    emergency_traffic uut (clk, reset, ped_button, emergency_input, light);

    always #5 clk = ~clk; 

    initial begin
        $dumpfile("emergency.vcd");
        $dumpvars(0, tb_emergency);
        
        clk = 0; reset = 1; ped_button = 0; emergency_input = 0;
        #10 reset = 0;

        // Normal cycle
        #50;

        // Scenario: Light is turning Red, but an Ambulance arrives!
        $display("Ambulance detected at 80ns!");
        #20 emergency_input = 1; 
        #20 emergency_input = 0;

        #100 $finish;
    end
endmodule
""")

sim/emergency.vcd
$date
	Fri Apr  3 11:18:47 2026
$end
$version
	Icarus Verilog
$end
$timescale
	1s
$end
$scope module tb_emergency $end
$var wire 3 ! light [2:0] $end
$var reg 1 " clk $end
$var reg 1 # emergency_input $end
$var reg 1 $ ped_button $end
$var reg 1 % reset $end
$scope module uut $end
$var wire 1 " clk $end
$var wire 1 # emergency_input $end
$var wire 1 $ ped_button $end
$var wire 1 % reset $end
$var reg 3 & light [2:0] $end
$var reg 2 ' next_state [1:0] $end
$var reg 2 ( state [1:0] $end
$var reg 4 ) timer [3:0] $end
$upscope $end
$upscope $end
$enddefinitions $end
#0
$dumpvars
b0 )
b0 (
b1 '
b1 &
1%
0$
0#
0"
b1 !
$end
#5
1"
#10
0"
0%
#15
b1 )
1"
#20
0"
#25
b10 )
1"
#30
0"
#35
b11 )
1"
#40
0"
#45
b100 )
1"
#50
0"
#55
b101 )
1"
#60
0"
#65
b110 )
1"
#70
0"
#75
b111 )
1"
#80
0"
1#
#85
b0 )
1"
#90
0"
#95
1"
#100
0"
0#
#105
b1 )
1"
#110
0"
#115
b10 )
1"
#120
0"
#125
b11 )
1"
#130
0"
#135
b100 )
1"
#140
0"
#145
b101 )
1"
#150
0"
#155
b110 )
1"
#160
0"
#165
b111 )
1"
#170
0"
#175
b1000 )
1"
#180
0"
#185
b1001 )
1"
#190
0"
#195
b1010 )
1"
